labbase2/__init__.py
labbase2/config.py
labbase2/database.py
labbase2/logging.py
labbase2/forms/__init__.py
labbase2/forms/filters.py
labbase2/forms/forms.py
labbase2/forms/render.py
labbase2/forms/rendering.py
labbase2/forms/utils.py
labbase2/forms/validators.py
labbase2/models/__init__.py
labbase2/models/antibody.py
labbase2/models/base_entity.py
labbase2/models/chemical.py
labbase2/models/comment.py
labbase2/models/consumable.py
labbase2/models/events.py
labbase2/models/fields.py
labbase2/models/file.py
labbase2/models/fly_stock.py
labbase2/models/import_job.py
labbase2/models/oligonucleotide.py
labbase2/models/plasmid.py
labbase2/models/request.py
labbase2/models/user.py
labbase2/models/mixins/__init__.py
labbase2/models/mixins/export.py
labbase2/models/mixins/filter.py
labbase2/models/mixins/importer.py
labbase2/models/mixins/sequence.py
labbase2/static/css/style.css
labbase2/static/css/style.css.map
labbase2/static/css/style.min.css
labbase2/static/css/style.scss
labbase2/static/images/avatar-f.webp
labbase2/static/images/avatar-m.webp
labbase2/static/vendors/bootstrap-5.2.3-dist/LICENSE
labbase2/static/vendors/bootstrap-5.2.3-dist/css/bootstrap.min.css
labbase2/static/vendors/bootstrap-5.2.3-dist/js/bootstrap.bundle.min.js
labbase2/static/vendors/bootstrap-5.2.3-dist/js/bootstrap.min.js
labbase2/static/vendors/jquery-3.7.1/LICENSE
labbase2/static/vendors/jquery-3.7.1/js/jquery-3.7.1.min.js
labbase2/static/vendors/jquery-ui/css/jquery-ui.min.css
labbase2/static/vendors/jquery-ui/css/jquery-ui.min.min.css
labbase2/static/vendors/jquery-ui/css/jquery-ui.structure.min.css
labbase2/static/vendors/jquery-ui/css/jquery-ui.structure.min.min.css
labbase2/static/vendors/jquery-ui/css/jquery-ui.theme.min.css
labbase2/static/vendors/jquery-ui/css/jquery-ui.theme.min.min.css
labbase2/static/vendors/jquery-ui/js/jquery-ui.min.js
labbase2/static/vendors/magnific-popup/LICENSE
labbase2/static/vendors/magnific-popup/css/magnific-popup.css
labbase2-0.3.0.dist-info/licenses/LICENSE
labbase2-0.3.0.dist-info/WHEEL
labbase2-0.3.0.dist-info/METADATA
labbase2-0.3.0.dist-info/RECORD
