Metadata-Version: 2.4
Name: labbase2
Version: 0.3.0
Summary: A database application to manage lab resources.
Author-email: Raphael Schleutker <raphaelschleutker@gmx.de>
Requires-Python: >=3.12
License-File: LICENSE
Requires-Dist: flask>=3.0.0
Requires-Dist: flask-security>5.6.1
Requires-Dist: flask-login>=0.6.3
Requires-Dist: flask-sqlalchemy>=3.0.0
Requires-Dist: flask-wtf>=1.2.1
Requires-Dist: pandas>=2.2.2
Requires-Dist: pillow>10.0.0
Requires-Dist: numpy>1.26.0
Requires-Dist: scikit-image>0.23.0
Requires-Dist: biopython>=1.78
Requires-Dist: email-validator>=1.2.1
Requires-Dist: openpyxl>=3.1.5
Requires-Dist: black ; extra == "dev"
Requires-Dist: isort ; extra == "dev"
Requires-Dist: pylint ; extra == "dev"
Requires-Dist: pytest>=8.3.4 ; extra == "test"
Provides-Extra: dev
Provides-Extra: test
